{
    "data": {
        "ids": [
            "3334227066666320"
        ],
        "name": "Dwelling in the Enfolding",
        "app_name": "Dwelling in the Enfolding",
        "type_name": "Application",
        "appstore_type": "Application",
        "category": "ENTERTAINMENT",
        "release_date": "2020-12-10T00:00:00",
        "description": "'Dwelling in the Enfolding’ is an interactive, 360° VR art experience by Matthew Burtner and Mona Kasra. The piece immerses participants within interconnecting glacial landscapes that were never inhabited yet inhabit imaginations. Within seemingly stationary but perpetually evolving landscapes, participants navigate a map of the terrain to bridge across disparate environments that belong to this unified whole.\n\nWhether on top of a vast ice field or deep in a mysterious ice cave, each encounter leads to distinct audiovisual experiences as participants’ gaze shapes and initiates unique sound events in the 3D space.\n\nWhile offering new ways to perceive the enfolding landscapes, this immersive encounter does not impose any singular experience or a particular way of navigating the environment. Instead, it models the ephemeral and sublime experience of being alone in nature, surrounded by landscapes not created for us or us.\n\n© Matthew Burtner & Mona Kasra, 2020, all rights reserved.",
        "markdown_desc": false,
        "developer": "Mona Kasra",
        "publisher": "The Anchorage Museum",
        "genres": [
            "Art/Creativity",
            "360 Experience (Non-game)"
        ],
        "input_devices": [
            "3DOF Controller"
        ],
        "games_modes": [
            "Single User"
        ],
        "languages": [
            "English"
        ],
        "platforms": [
            "Meta Quest 3",
            "Meta Quest Pro",
            "Meta Quest 2",
            "Meta Quest"
        ],
        "player_modes": [],
        "tags": [],
        "hist": [
            {
                "rating": 1,
                "votes": 0
            },
            {
                "rating": 2,
                "votes": 1
            },
            {
                "rating": 3,
                "votes": 0
            },
            {
                "rating": 4,
                "votes": 1
            },
            {
                "rating": 5,
                "votes": 2
            }
        ],
        "comfort": "COMFORTABLE_FOR_MOST",
        "iarc": {
            "age_rating": "Everyone",
            "descriptors": [],
            "elements": [],
            "icon": "https://scontent.oculuscdn.com/v/t64.5771-25/12482345_233896350376075_8399588285755686912_n.png?_nc_cat=1&ccb=1-7&_nc_sid=6e7a0a&_nc_ohc=U7AfMsqPUrIAX_U1PQt&_nc_ht=scontent.oculuscdn.com&oh=00_AfCrWEHNF1Ar2Dq5GRBite797ISteIubE04WKKYF7QvLtw&oe=65814E4D"
        },
        "platform": "ANDROID",
        "internet_connection": "NOT_REQUIRED",
        "website": "http://dwellingintheenfolding.com/",
        "icon": "https://scontent.oculuscdn.com/v/t64.5771-25/39031468_331550568126196_6532294926713516529_n.jpg?stp=dst-jpg_q92_s56x56&_nc_cat=110&ccb=1-7&_nc_sid=6e7a0a&_nc_ohc=O3pzm6kYic0AX8ApDD2&_nc_ht=scontent.oculuscdn.com&oh=00_AfCe47xVqs61Bm7atKunA3BqcVPdxQ711XUFHoDC_AycbA&oe=6581DEA0",
        "banner": "https://scontent.oculuscdn.com/v/t64.5771-25/39031368_1191530391247919_7595767118020783696_n.jpg?stp=dst-jpg_q92_s2048x2048&_nc_cat=105&ccb=1-7&_nc_sid=6e7a0a&_nc_ohc=P9o2tIX4D1YAX86FRF1&_nc_ht=scontent.oculuscdn.com&oh=00_AfCoXbtUlunwPNTTOG8uRefww1MwHcsmCAHt74S97MUZ6g&oe=6581DB73",
        "screenshots": [
            "https://scontent.oculuscdn.com/v/t64.5771-25/39031529_1245048632495420_4805627068348533744_n.jpg?stp=dst-jpg_q92_s1440x1440&_nc_cat=101&ccb=1-7&_nc_sid=6e7a0a&_nc_ohc=NsV9MeiJQ8MAX_jDeQe&_nc_ht=scontent.oculuscdn.com&oh=00_AfCDoXcXJgroYQjIrBfyAKK8rqPGTdZZOLQeKEW586z3MQ&oe=6580F214",
            "https://scontent.oculuscdn.com/v/t64.5771-25/38974633_273662617134013_5562514352466862071_n.jpg?stp=dst-jpg_q92_s1440x1440&_nc_cat=103&ccb=1-7&_nc_sid=6e7a0a&_nc_ohc=fPuh5VGun-4AX9ZtnGY&_nc_ht=scontent.oculuscdn.com&oh=00_AfCH4oAuHaJjdjE59us-hn-nF_nj3idItI-nyDxWgZEc3A&oe=65824E82",
            "https://scontent.oculuscdn.com/v/t64.5771-25/38982715_343249890115783_3968024748972875449_n.jpg?stp=dst-jpg_q92_s1440x1440&_nc_cat=107&ccb=1-7&_nc_sid=6e7a0a&_nc_ohc=sIGX9xOj1t8AX_Mb_mC&_nc_ht=scontent.oculuscdn.com&oh=00_AfBRiZ6vcTLrszB7I17g8ObxO10Y4RBaGerTyH6-EJzuIw&oe=6582DB45",
            "https://scontent.oculuscdn.com/v/t64.5771-25/57568668_404167533910625_2631133982216326007_n.jpg?stp=dst-jpg_q92_s1440x1440&_nc_cat=107&ccb=1-7&_nc_sid=6e7a0a&_nc_ohc=TEaGDgxm-v4AX-3sfwj&_nc_ht=scontent.oculuscdn.com&oh=00_AfDKFZMrzho_5u7j2M6dz0aXyKgR-uJbDpwTJ2SRslR_UQ&oe=658277EB",
            "https://scontent.oculuscdn.com/v/t64.5771-25/39031311_805918723500954_405090875188791800_n.jpg?stp=dst-jpg_q92_s1440x1440&_nc_cat=101&ccb=1-7&_nc_sid=6e7a0a&_nc_ohc=fMRPsS-tLWQAX_ZlSPs&_nc_ht=scontent.oculuscdn.com&oh=00_AfBCx9cEv1vwb7Ux2mMoiVXN07g6Qjm2JXtNIDCpgRJoyA&oe=6581DD89"
        ],
        "trailer": {
            "thumbnail": "https://scontent.oculuscdn.com/v/t64.5771-25/38982446_887239365418837_8606192943718080516_n.jpg?stp=dst-jpg_q92_s1440x1440&_nc_cat=111&ccb=1-7&_nc_sid=6e7a0a&_nc_ohc=BOEQ9RLEgrwAX83uFCd&_nc_ht=scontent.oculuscdn.com&oh=00_AfBfu94CVETvnpnqfXqXhYen3gGIbJGLgrWLlG9dtVBMoA&oe=6581BDF0",
            "url": "https://scontent.oculuscdn.com/v/t64.7195-25/75210399_369843981093068_6172156595916301058_n.mp4?_nc_cat=104&ccb=1-7&_nc_sid=b20b63&_nc_ohc=l2i7U8H--p0AX-y1Xd3&_nc_ht=scontent.oculuscdn.com&oh=00_AfBNqXHxMtH9y4CaNSNWouNHxtfofpRTA7-XLh2tWc_5eg&oe=65820352"
        },
        "has_ads": false,
        "require_360_sensor": false,
        "votes": 4,
        "rating": 4.0,
        "is_available": true,
        "is_free": true
    }
}