{
    "data": {
        "ids": [
            "1940786632644691"
        ],
        "name": "CenarioVR",
        "app_name": "CenarioVR",
        "type_name": "Application",
        "appstore_type": "Application",
        "category": "APPS",
        "release_date": "2018-11-28T00:00:00",
        "description": "CenarioVR is a powerful and easy-to-use virtual reality training tool that enables you to drive engagement, retention, and performance.\nIts intuitive design allows users to generate interactive, immersive scenarios using 360° images and videos. These scenarios can be viewed using the CenarioVR App for Oculus.\n\nYou can create your own VR experiences with CenarioVR by signing up at https://CenarioVR.com.",
        "markdown_desc": false,
        "developer": "eLearning Brothers",
        "publisher": "eLearning Brothers",
        "genres": [
            "Educational",
            "360 Experience (Non-game)",
            "Travel"
        ],
        "input_devices": [
            "3DOF Controller"
        ],
        "games_modes": [
            "Single user"
        ],
        "languages": [
            "English"
        ],
        "platforms": [
            "Meta Quest 3",
            "Meta Quest Pro",
            "Meta Quest 2",
            "Meta Quest"
        ],
        "player_modes": [],
        "tags": [
            "EDUCATIONAL"
        ],
        "hist": [
            {
                "rating": 1,
                "votes": 2
            },
            {
                "rating": 2,
                "votes": 1
            },
            {
                "rating": 3,
                "votes": 5
            },
            {
                "rating": 4,
                "votes": 0
            },
            {
                "rating": 5,
                "votes": 3
            }
        ],
        "comfort": "COMFORTABLE_FOR_MOST",
        "iarc": {
            "age_rating": "Everyone",
            "descriptors": [],
            "elements": [],
            "icon": "https://scontent.oculuscdn.com/v/t64.5771-25/12482345_233896350376075_8399588285755686912_n.png?_nc_cat=110&ccb=1-7&_nc_sid=6e7a0a&_nc_ohc=_tl-MF67bbUAX9kYkeE&_nc_ht=scontent.oculuscdn.com&oh=00_AfC8ZFANB2qNr6AJmlEsk_hZ4y9IW7VXWtUJFpbaA9T3ZA&oe=657D59CD"
        },
        "platform": "ANDROID",
        "internet_connection": "REQUIRED",
        "website": "https://cenariovr.com/",
        "icon": "https://scontent.oculuscdn.com/v/t64.5771-25/39031337_1553658881462038_8502174542506210655_n.jpg?stp=dst-jpg_q92_s56x56&_nc_cat=103&ccb=1-7&_nc_sid=6e7a0a&_nc_ohc=A5A85l1r0_4AX8HLR3m&_nc_ht=scontent.oculuscdn.com&oh=00_AfAp2rTnYvM9y60Ok8-j17fQdBf1IgBuR7hwLBxDPuPSEg&oe=657C61B1",
        "banner": "https://scontent.oculuscdn.com/v/t64.5771-25/39036607_3234903393260282_8446180659543206708_n.jpg?stp=dst-jpg_q92_s2048x2048&_nc_cat=103&ccb=1-7&_nc_sid=6e7a0a&_nc_ohc=OGGwo2n_8KAAX93s0MN&_nc_ht=scontent.oculuscdn.com&oh=00_AfDaeUxePuiUNcHpYSnaO_RbOXFyvowJiTkCKwlL0W4eUA&oe=657D6414",
        "screenshots": [
            "https://scontent.oculuscdn.com/v/t64.5771-25/39031622_248838669143141_8367897697763459072_n.jpg?stp=dst-jpg_q92_s1440x1440&_nc_cat=100&ccb=1-7&_nc_sid=6e7a0a&_nc_ohc=MUlGSk30hasAX9OdGgW&_nc_ht=scontent.oculuscdn.com&oh=00_AfAE6pwIPPg_OuYjSuAC8OhW8nli1aiHfuvGHbxjJsS_2w&oe=657C3FB4",
            "https://scontent.oculuscdn.com/v/t64.5771-25/38974564_259546014736134_4455489667168468992_n.jpg?stp=dst-jpg_q92_s1440x1440&_nc_cat=102&ccb=1-7&_nc_sid=6e7a0a&_nc_ohc=A6zNFmaR_kMAX98YysS&_nc_ht=scontent.oculuscdn.com&oh=00_AfCmVEawty-ifArWpk9-40iiF-QSkVkRgjPfy3Tj-9E76A&oe=657D8166",
            "https://scontent.oculuscdn.com/v/t64.5771-25/38974440_532703940516156_1667319773324640256_n.jpg?stp=dst-jpg_q92_s1440x1440&_nc_cat=106&ccb=1-7&_nc_sid=6e7a0a&_nc_ohc=uMFWom-qpn0AX_2689b&_nc_ht=scontent.oculuscdn.com&oh=00_AfCyimRvSKbrTGeOltZu7cZk3ZG6kcqN0NP8NR8T_-xeRQ&oe=657DFE3D",
            "https://scontent.oculuscdn.com/v/t64.5771-25/38974439_331361820766881_2668650888255504384_n.jpg?stp=dst-jpg_q92_s1440x1440&_nc_cat=105&ccb=1-7&_nc_sid=6e7a0a&_nc_ohc=iz8IkGyo-0cAX_6OqXw&_nc_ht=scontent.oculuscdn.com&oh=00_AfAvmg_nElltGXmcK3p12SoX5cTeEfMa9aEn6AXowCBwcQ&oe=657D5B60",
            "https://scontent.oculuscdn.com/v/t64.5771-25/38974678_1932227066838931_796777928749744128_n.jpg?stp=dst-jpg_q92_s1440x1440&_nc_cat=100&ccb=1-7&_nc_sid=6e7a0a&_nc_ohc=ncjjyAgPpvwAX8ukKm1&_nc_ht=scontent.oculuscdn.com&oh=00_AfAPNtpXy2tlMWEi2qQC5VjU6TlaPDnpczHcyLHt2w3ZxA&oe=657C32AC"
        ],
        "trailer": {
            "thumbnail": "https://scontent.oculuscdn.com/v/t64.5771-25/75210395_664688807516383_2947177450274479069_n.jpg?stp=dst-jpg_q92_s1440x1440&_nc_cat=103&ccb=1-7&_nc_sid=6e7a0a&_nc_ohc=9IuhMo7X0ZgAX8lZ8rm&_nc_ht=scontent.oculuscdn.com&oh=00_AfBqDRvAYSl1d-V_XPoSQmmDjKyF9Nwy2vlFAut5eU7Swg&oe=657D38E8",
            "url": "https://scontent.oculuscdn.com/v/t64.7195-25/39031467_419215435734920_2496537090619579847_n.mp4?_nc_cat=100&ccb=1-7&_nc_sid=b20b63&_nc_ohc=lKdZBotHVhIAX8Nt9VT&_nc_ht=scontent.oculuscdn.com&oh=00_AfDiVFCfELzEBA3rGgEoNpNa_kErkjaM57vc53t5vDDUEQ&oe=657D04FD"
        },
        "has_ads": false,
        "require_360_sensor": false,
        "votes": 11,
        "rating": 3.090909090909091,
        "is_available": true,
        "is_free": true
    }
}