{
    "data": {
        "id": "1678863422218752",
        "app_name": "INL Nuclear Science and Technology Facilities",
        "release_date": "1980-01-01T00:00:00.000Z",
        "description": "INL is the nation’s lead laboratory for nuclear energy research, development, demonstration and deployment and is engaged in the mission of ensuring the nation’s energy security with safe, competitive and sustainable energy systems and unique national and homeland security capabilities.\nINL is part of the U.S. Department of Energy’s complex of national laboratories. The laboratory performs work in each of the strategic goal areas of DOE: energy, national security, science and environment.INL is managed by Battelle Energy Alliance for the Department of Energy’s Office of Nuclear Energy. This 360 tour provides a look inside one of the worlds leading nuclear research centers in action.",
        "developer": "Gravis Tech",
        "publisher": "Gravis Tech",
        "genres": [
            "Non-Game Experience"
        ],
        "devices": [],
        "modes": [
            "Single User"
        ],
        "languages": [
            "English",
            "English (US)"
        ],
        "platforms": [
            "Go",
            "Gear VR"
        ],
        "player_modes": [],
        "tags": [],
        "hist": [
            {
                "rating": 1,
                "votes": 0
            },
            {
                "rating": 2,
                "votes": 4
            },
            {
                "rating": 3,
                "votes": 2
            },
            {
                "rating": 4,
                "votes": 1
            },
            {
                "rating": 5,
                "votes": 3
            }
        ],
        "comfort": "COMFORTABLE_FOR_SOME",
        "iarc": {
            "age_rating": "Everyone",
            "descriptors": [],
            "elements": [],
            "iarc_icon": "12482345_233896350376075_8399588285755686912_n.png"
        },
        "internet_connection": "NOT_REQUIRED",
        "website": "https://360.gravistech.com/",
        "app_images": {
            "cover_landscape": "39001705_1190031177816189_3767924592023175168_n.png",
            "cover_portrait": "38982447_201714404037340_9067104801455603712_n.png",
            "cover_square": "38982608_2272466046117336_3029585994052534272_n.png",
            "hero": "38974893_2169951606594693_8851410251065327616_n.png",
            "icon": "38974511_336904180427230_7798386198249996288_n.png",
            "immersive_layer_backdrop": null,
            "immersive_layer_logo": null,
            "logo_transparent": "38974789_493992727779302_3643755442523340800_n.png"
        },
        "changelog": [
            {
                "version": "1.31",
                "change_log": "Added application.exit to fulfill VRC.Mobile.Security.1"
            },
            {
                "version": "1.3",
                "change_log": "Fixed entitlement check.  Fixed back button behavior.  Fixed extra permissions requested.\r\nIncremented version."
            }
        ],
        "on_rookie": false,
        "general_update": 476257,
        "genre_update": 475633,
        "device_update": 475633,
        "mode_update": 475633,
        "language_update": 475633,
        "platform_update": 475633,
        "player_mode_update": 475633,
        "changelog_update": 475633,
        "keyword_update": 475633,
        "tag_update": 475633,
        "rating_update": 475777,
        "iarc_detail_update": 475633,
        "keywords": [],
        "last_update": 476257,
        "category": "APPS",
        "votes": 10,
        "rating": 3.3,
        "weighted_rating": 3.4
    },
    "errors": []
}