{
    "data": {
        "id": "6420558991382261",
        "app_name": "Microsoft Excel",
        "release_date": "2023-12-14T00:00:00.000Z",
        "description": "Microsoft Excel lets you easily create, view, edit, and share your spreadsheets. With Excel, the most powerful tools are right at your fingertips. Whether it be data analysis, accounting, or auditing, Excel allows you to work confidently with anyone, anywhere. \n\nReview spreadsheets and run analyses on the go,and customize them the way you want with robust formatting options and other amazing features. \n",
        "developer": "Microsoft Corp.",
        "publisher": "Microsoft",
        "genres": [
            "Casual",
            "Business, Productivity & Utility"
        ],
        "devices": [
            "Hand Tracking",
            "Tracked keyboard"
        ],
        "modes": [
            "Single User"
        ],
        "languages": [
            "English"
        ],
        "platforms": [
            "Meta Quest 3",
            "Meta Quest Pro",
            "Meta Quest 2",
            "Meta Quest"
        ],
        "player_modes": [],
        "tags": [
            "Enterprise"
        ],
        "hist": [
            {
                "rating": 1,
                "votes": 7
            },
            {
                "rating": 2,
                "votes": 1
            },
            {
                "rating": 3,
                "votes": 1
            },
            {
                "rating": 4,
                "votes": 0
            },
            {
                "rating": 5,
                "votes": 4
            }
        ],
        "comfort": "COMFORTABLE_FOR_MOST",
        "iarc": {
            "age_rating": "Everyone",
            "descriptors": [],
            "elements": [],
            "iarc_icon": "12482345_233896350376075_8399588285755686912_n.png"
        },
        "internet_connection": "REQUIRED",
        "website": "https://www.office.com/",
        "app_images": {
            "cover_landscape": "39001730_840254584773525_8320168088042662684_n.png",
            "cover_portrait": "75416837_304624155817993_8771517673269828374_n.png",
            "cover_square": "75395601_403774581976504_4925030991763117600_n.png",
            "hero": "39001660_561383382817302_2270084032989505731_n.png",
            "icon": "39035373_239966542094607_2733377485074663596_n.png",
            "immersive_layer_backdrop": null,
            "immersive_layer_logo": null,
            "logo_transparent": "75272208_402473558772892_8715894043989005181_n.png"
        },
        "changelog": [],
        "on_rookie": false,
        "general_update": 475561,
        "genre_update": 474685,
        "device_update": 474685,
        "mode_update": 474685,
        "language_update": 474685,
        "platform_update": 474685,
        "player_mode_update": 474685,
        "changelog_update": 475000,
        "keyword_update": 474685,
        "tag_update": 474880,
        "rating_update": 475561,
        "iarc_detail_update": 475000,
        "keywords": [],
        "last_update": 475561,
        "category": "APPS",
        "votes": 13,
        "rating": 2.461538,
        "weighted_rating": 2.9
    },
    "errors": []
}