{
    "data": {
        "id": "7346569492068338",
        "app_name": "Monke Jumpers",
        "release_date": "1980-01-01T00:00:00.000Z",
        "description": "Climb and jump like a monkey with your friends.",
        "developer": "yessir monkey",
        "publisher": "Pallidrone1",
        "genres": [
            "Adventure",
            "Social"
        ],
        "devices": [
            "Touch Controllers"
        ],
        "modes": [
            "Multiplayer"
        ],
        "languages": [
            "English"
        ],
        "platforms": [
            "Meta Quest 3",
            "Meta Quest Pro",
            "Meta Quest 2"
        ],
        "player_modes": [
            "STANDING",
            "ROOM_SCALE"
        ],
        "tags": [],
        "hist": [
            {
                "rating": 1,
                "votes": 1
            },
            {
                "rating": 2,
                "votes": 0
            },
            {
                "rating": 3,
                "votes": 1
            },
            {
                "rating": 4,
                "votes": 3
            },
            {
                "rating": 5,
                "votes": 5
            }
        ],
        "comfort": "NOT_RATED",
        "iarc": {
            "age_rating": "Everyone",
            "descriptors": [],
            "elements": [
                "Users Interact"
            ],
            "iarc_icon": "12482345_233896350376075_8399588285755686912_n.png"
        },
        "internet_connection": "REQUIRED",
        "website": "https://yessirmonkeysstudio.godaddysites.com/",
        "app_images": {
            "cover_landscape": "75375081_3204099766401060_1359130802359115626_n.png",
            "cover_portrait": "38974899_2183443658683023_6897896025094100189_n.png",
            "cover_square": "38982556_1089184008800750_8062248543598792874_n.png",
            "hero": "75250461_729768255994559_5529056916369815724_n.png",
            "icon": "38982675_957698112631487_8089269191144372314_n.png",
            "immersive_layer_backdrop": null,
            "immersive_layer_logo": null,
            "logo_transparent": "75196218_3535429956708414_1704705208020642350_n.png"
        },
        "changelog": [
            {
                "version": "0.9",
                "change_log": "Added gtag map"
            }
        ],
        "on_rookie": false,
        "general_update": 478969,
        "genre_update": 478969,
        "device_update": 478969,
        "mode_update": 478969,
        "language_update": 478969,
        "platform_update": 478969,
        "player_mode_update": 478969,
        "changelog_update": 478969,
        "keyword_update": 478969,
        "tag_update": 478969,
        "rating_update": 478969,
        "iarc_detail_update": 478969,
        "keywords": [],
        "last_update": 478969,
        "category": "GAMES",
        "votes": 10,
        "rating": 4.1,
        "weighted_rating": 3.8
    },
    "errors": []
}