{
    "data": {
        "id": "8057106377654217",
        "app_name": "Chimpies",
        "release_date": "1980-01-01T00:00:00.000Z",
        "description": "Chimpies is a casual game with horror connected to it! Run around with others have fun and play with a people! There is so much to do like run around the caves play with your friends in a private code and lots more to do!",
        "developer": "Robot Kyle",
        "publisher": "AcornStudios",
        "genres": [
            "Action",
            "Horror",
            "Casual"
        ],
        "devices": [
            "Touch Controllers"
        ],
        "modes": [
            "Multiplayer"
        ],
        "languages": [
            "English"
        ],
        "platforms": [
            "Meta Quest 3S",
            "Meta Quest 3",
            "Meta Quest Pro",
            "Meta Quest 2"
        ],
        "player_modes": [
            "ROOM_SCALE",
            "STANDING"
        ],
        "tags": [],
        "hist": [
            {
                "rating": 1,
                "votes": 0
            },
            {
                "rating": 2,
                "votes": 0
            },
            {
                "rating": 3,
                "votes": 0
            },
            {
                "rating": 4,
                "votes": 0
            },
            {
                "rating": 5,
                "votes": 0
            }
        ],
        "comfort": "COMFORTABLE_FOR_SOME",
        "iarc": {
            "age_rating": "Teen",
            "descriptors": [
                "Violence",
                "Blood"
            ],
            "elements": [
                "Users Interact",
                "In-Game Purchases"
            ],
            "iarc_icon": "12138850_1786874088228955_5598594603113512960_n.png"
        },
        "internet_connection": "REQUIRED",
        "website": "https://sites.google.com/view/chimpies/home",
        "app_images": {
            "cover_landscape": "75612004_878044890930557_1085681081145433003_n.png",
            "cover_portrait": "38982533_557109946751148_2191633866005807503_n.png",
            "cover_square": "75441576_871991824641858_1182463866565706363_n.png",
            "hero": "39031538_537173612030863_6946884203620855378_n.png",
            "icon": "39031655_888247743363929_3140133779968576043_n.png",
            "immersive_layer_backdrop": null,
            "immersive_layer_logo": null,
            "logo_transparent": "75284540_1677542779727175_833552459790049997_n.png"
        },
        "changelog": [],
        "on_rookie": false,
        "general_update": 480073,
        "genre_update": 480073,
        "device_update": 480073,
        "mode_update": 480073,
        "language_update": 480073,
        "platform_update": 480073,
        "player_mode_update": 480073,
        "changelog_update": 480073,
        "keyword_update": 480073,
        "tag_update": 480073,
        "rating_update": 480073,
        "iarc_detail_update": 480073,
        "keywords": [],
        "last_update": 480073,
        "category": "GAMES",
        "votes": 0,
        "rating": 0.0,
        "weighted_rating": 3.4
    },
    "errors": []
}