{
    "data": {
        "id": "9298251876913852",
        "app_name": "Layout",
        "release_date": "2024-03-31T00:00:00.000Z",
        "description": "Visualize your home like never before with Layout, powered by mixed reality on Meta Quest 3. Layout features a suite of tools designed to help you spatially measure, align and visualize real world objects directly in your physical space.",
        "developer": "Project Curio",
        "publisher": "Meta",
        "genres": [
            "Business, Productivity & Utility"
        ],
        "devices": [
            "Touch Controllers"
        ],
        "modes": [
            "Single User"
        ],
        "languages": [
            "English",
            "English (US)",
            "English (UK)",
            "Spanish (Spain)"
        ],
        "platforms": [
            "Meta Quest Pro",
            "Meta Quest 3"
        ],
        "player_modes": [
            "ROOM_SCALE"
        ],
        "tags": [],
        "hist": [
            {
                "rating": 1,
                "votes": 1
            },
            {
                "rating": 2,
                "votes": 0
            },
            {
                "rating": 3,
                "votes": 0
            },
            {
                "rating": 4,
                "votes": 1
            },
            {
                "rating": 5,
                "votes": 5
            }
        ],
        "comfort": "COMFORTABLE_FOR_MOST",
        "iarc": {
            "age_rating": "Everyone",
            "descriptors": [],
            "elements": [],
            "iarc_icon": "12482345_233896350376075_8399588285755686912_n.png"
        },
        "internet_connection": "NOT_REQUIRED",
        "website": "https://www.meta.com/",
        "app_images": {
            "cover_landscape": "38982620_1721211351697079_3951680791084614112_n.png",
            "cover_portrait": "38974513_311072608558470_1403078061139550233_n.png",
            "cover_square": "38974663_905363951002968_7444032958619317353_n.png",
            "hero": "39031464_1063733948015874_249454301739064375_n.png",
            "icon": "38984440_888543999153888_2360651598313884217_n.png",
            "immersive_layer_backdrop": null,
            "immersive_layer_logo": null,
            "logo_transparent": "39035341_6336003499829798_2061769858969780293_n.png"
        },
        "changelog": [],
        "on_rookie": false,
        "general_update": 475705,
        "genre_update": 475153,
        "device_update": 475153,
        "mode_update": 475153,
        "language_update": 475153,
        "platform_update": 475153,
        "player_mode_update": 475153,
        "changelog_update": 475153,
        "keyword_update": 475153,
        "tag_update": 475153,
        "rating_update": 475705,
        "iarc_detail_update": 475153,
        "keywords": [],
        "last_update": 475705,
        "category": "SYSTEM",
        "votes": 7,
        "rating": 4.285714,
        "weighted_rating": 3.8
    },
    "errors": []
}