{
    "package": "com.ccpgames.gunjack",
    "data": {
        "id": "969815736436279",
        "name": "GUNJACK",
        "app_name": "GUNJACK",
        "type_name": "Application",
        "appstore_type": "Application",
        "category": "GAMES",
        "release_date": "2015-11-19T00:00:00",
        "description": "“‘Gunjack’ is one of the best Gear VR launch titles.” 5/5 -Upload VR\n\n“…one of the best-looking things on the Gear VR.” -Polygon\n\n“Gunjack sets the bar for Gear VR turret shooters.” 4/5 –Road To VR \n\nGunjack is a visually stunning virtual reality arcade shooter set in the sprawling EVE science fiction universe. Jump into your heavy weapons turret, power up your guns, and defend your mining platform from deadly waves of enemy ships determined to blast you and your crew into oblivion. With its intuitive controls and intense, immersive action, Gunjack is the ultimate pick-up-and-play VR experience.\n\nGunjack supports English, German, French, Italian, Spanish and Korean.\n\nNOTICE: Gaming experience will be improved on later generation phones and we recommend Android 5.1.1 or greater for best performance.\n\nUse of this application is governed by CCP’s end user license agreement. This is available at http://www.gunjack.com/eula/",
        "markdown": false,
        "publisher": "CCP Games",
        "genres": [
            "Arcade",
            "Shooter"
        ],
        "devices": [
            "Touchpad",
            "Gamepad"
        ],
        "modes": [
            "Single User"
        ],
        "languages": [
            "English"
        ],
        "platforms": [
            "Meta Quest 3",
            "Meta Quest Pro",
            "Meta Quest 2",
            "Meta Quest"
        ],
        "player_modes": [],
        "tags": [
            "Essentials"
        ],
        "hist": [
            {
                "rating": 1,
                "votes": 485
            },
            {
                "rating": 2,
                "votes": 383
            },
            {
                "rating": 3,
                "votes": 1127
            },
            {
                "rating": 4,
                "votes": 3300
            },
            {
                "rating": 5,
                "votes": 6788
            }
        ],
        "comfort": "COMFORTABLE_FOR_MOST",
        "iarc": {
            "age_rating": "Everyone 10+",
            "descriptors": [
                "Mild Language",
                "Fantasy Violence"
            ],
            "elements": [],
            "iarc_icon": "12386444_352227485138085_8354695406382219264_n.png"
        },
        "platform": "ANDROID",
        "internet_connection": "NOT_REQUIRED",
        "website": "http://www.GUNJACK.com/",
        "icon": "12138908_883708178361931_1125786366_n.jpg",
        "banner": "11162739_1644871639089029_1282263076_n.jpg",
        "has_ads": false,
        "sensor_req": false,
        "votes": 12083,
        "rating": 4.284698,
        "weighted_rating": 4.284089,
        "is_available": false,
        "is_free": false
    }
}