{
    "data": {
        "id": "1115233775178991",
        "name": "Wizards 2: Better Dead Than Red",
        "app_name": "Wizards 2: Better Dead Than Red",
        "type_name": "Application",
        "appstore_type": "Application",
        "category": "GAMES",
        "release_date": "2017-08-09T00:00:00",
        "description": "The Techno-Viking scourge has returned for revenge and is more bloodthirsty than ever! Take control of your last line of defense to defeat your foes!\n\nEliminate hordes of planes, tanks, and mechs with ten unique weapons, from conventional cannons and launchers to plasma whips and photon torpedoes. Upgrade your equipment to survive ever-stronger waves of deadly enemies!",
        "markdown": false,
        "developer": "Terrasect Mobile, LLC",
        "publisher": "Terrasect Mobile, LLC",
        "genres": [
            "Action",
            "Arcade",
            "Shooter"
        ],
        "devices": [
            "Touchpad"
        ],
        "modes": [
            "Single User"
        ],
        "languages": [
            "English"
        ],
        "platforms": [
            "Meta Quest 3",
            "Meta Quest Pro",
            "Meta Quest 2",
            "Meta Quest"
        ],
        "player_modes": [],
        "tags": [],
        "hist": [
            {
                "rating": 1,
                "votes": 0
            },
            {
                "rating": 2,
                "votes": 0
            },
            {
                "rating": 3,
                "votes": 0
            },
            {
                "rating": 4,
                "votes": 0
            },
            {
                "rating": 5,
                "votes": 2
            }
        ],
        "comfort": "COMFORTABLE_FOR_SOME",
        "iarc": {
            "age_rating": "Everyone 10+",
            "descriptors": [
                "Mild Blood",
                "Fantasy Violence"
            ],
            "elements": [],
            "iarc_icon": "12386444_352227485138085_8354695406382219264_n.png"
        },
        "platform": "ANDROID",
        "internet_connection": "NOT_REQUIRED",
        "website": "http://www.terrasect.com/wizards-2",
        "icon": "11162688_1979867345580476_767211322344472576_n.jpg",
        "banner": "39001680_249857625687095_8402232752954408960_n.jpg",
        "logo_portrait": "com.terrasect.wizards2.jpg",
        "logo_landscape": "com.terrasect.wizards2.jpg",
        "has_ads": false,
        "sensor_req": false,
        "votes": 2,
        "rating": 5.0,
        "is_available": true,
        "is_free": false
    }
}