{
    "package": "com.bunkersurfer.mastershowvr",
    "data": {
        "id": "5957586430947789",
        "additional_ids": [],
        "name": "Master Show VR",
        "app_name": "Master Show VR",
        "type_name": "Application",
        "appstore_type": "Application",
        "category": null,
        "release_date": "2022-12-22T00:00:00",
        "description": "Two game modes: Stage simulator & Stage defender\n\n36 characters to create your stage.\n9 musicians with these instruments: electric guitar, drums, bass guitar, music keyboard, piano, violin, bongo drum, trumpet and saxophone.\n\n18 singers of different styles in two genres, female and male.\nK-pop, pop, classic pop, rap, reggae, ballad, rock, guitarist and pianist.\n\n9 fun dancers and chorus girls to set the stage:\nDancing girl, dancing boy, bear, happy face, led costume, female choir, male choir, mysterious choristers.",
        "markdown": false,
        "developer": "Bunker Surfer",
        "publisher": "Bunker Surfer",
        "genres": [
            "Simulation"
        ],
        "devices": [
            "Touch Controllers"
        ],
        "modes": [
            "Single User"
        ],
        "languages": [
            "English"
        ],
        "platforms": [
            "Meta Quest 3",
            "Meta Quest Pro",
            "Meta Quest 2",
            "Meta Quest"
        ],
        "player_modes": [
            "STANDING"
        ],
        "tags": [],
        "hist": [
            {
                "rating": 1,
                "votes": 0
            },
            {
                "rating": 2,
                "votes": 0
            },
            {
                "rating": 3,
                "votes": 0
            },
            {
                "rating": 4,
                "votes": 0
            },
            {
                "rating": 5,
                "votes": 0
            }
        ],
        "comfort": "NOT_RATED",
        "age_rating": null,
        "iarc": {
            "age_rating": "Everyone 10+",
            "descriptors": [
                "Fantasy Violence"
            ],
            "elements": [],
            "iarc_icon": "12386444_352227485138085_8354695406382219264_n.png"
        },
        "platform": "ANDROID_6DOF",
        "internet_connection": "NOT_REQUIRED",
        "website": "https://bunkersurfer.com/",
        "app_images": {
            "cover_landscape": "38982530_5231933670239417_568201240713931062_n.png",
            "cover_portrait": "39003253_3311966962355705_2308030818535404874_n.png",
            "cover_square": "38984464_1586881051778507_7903109712564467523_n.png",
            "hero": "38974574_642553990954005_43340701097289857_n.png",
            "icon": "38982474_3101262146686622_8526628240314719248_n.png",
            "immersive_layer_backdrop": null,
            "immersive_layer_logo": null,
            "logo_transparent": "75322605_1033849221342023_2219858641974903660_n.png"
        },
        "translations": [],
        "changelog": [],
        "keywords": [],
        "has_ads": false,
        "sensor_req": false,
        "is_demo_of": null,
        "on_rookie": false,
        "votes": 0,
        "rating": 0.0,
        "weighted_rating": 3.85,
        "is_available": true,
        "is_free": false
    },
    "errors": []
}